{"url":"/best","label":"베스트","httpStatus":200,"consoleErrors":["[PageError] Failed to execute 'appendChild' on 'Node': Invalid or unexpected token","[PageError] Failed to execute 'appendChild' on 'Node': Invalid or unexpected token"],"performance":{"fcp":1540,"lcp":1540,"cls":0,"ttfb":10,"domLoadTime":1454},"hasH1":true,"h1Text":"인기글 — 우나어 베스트","ogTitle":"인기글 | 우나어","ogDescription":"우나어 커뮤니티에서 가장 인기 있는 글 모음","ogImage":"https://www.age-doesnt-matter.com/icon-1024.png","canonicalUrl":"https://age-doesnt-matter.com/best","imagesMissingAlt":0,"issues":[]}